torch_geopooling/_C.cpython-311-darwin.so
torch_geopooling/__init__.py
torch_geopooling/py.typed
torch_geopooling/return_types.py
torch_geopooling/tiling.py
torch_geopooling/transforms.py
torch_geopooling/transforms_test.py
torch_geopooling/__bind__/python_module.cc
torch_geopooling/functional/__init__.py
torch_geopooling/functional/embedding.py
torch_geopooling/functional/embedding_test.py
torch_geopooling/functional/pooling.py
torch_geopooling/functional/pooling_test.py
torch_geopooling/nn/__init__.py
torch_geopooling/nn/embedding.py
torch_geopooling/nn/embedding_test.py
torch_geopooling/nn/pooling.py
torch_geopooling/nn/pooling_test.py
torch_geopooling-1.2.0.dist-info/licenses/LICENSE
torch_geopooling-1.2.0.dist-info/METADATA
torch_geopooling-1.2.0.dist-info/WHEEL
torch_geopooling-1.2.0.dist-info/dependency_links.txt
torch_geopooling-1.2.0.dist-info/top_level.txt
torch_geopooling-1.2.0.dist-info/RECORD
