Metadata-Version: 2.4
Name: torch-geopooling
Version: 1.2.0
Summary: The geospatial pooling modules for neural networks in PyTorch
Author-email: Yakau Bubnou <girokompass@gmail.com>
License:                     GNU GENERAL PUBLIC LICENSE
Project-URL: Funding, https://github.com/sponsors/ybubnov
Project-URL: Homepage, https://github.com/ybubnov/torch_geopooling
Project-URL: Source, https://github.com/ybubnov/torch_geopooling
Classifier: Development Status :: 5 - Production/Stable
Classifier: Intended Audience :: Developers
Classifier: License :: OSI Approved :: GNU General Public License v3 (GPLv3)
Classifier: Topic :: Scientific/Engineering
Classifier: Topic :: Scientific/Engineering :: Artificial Intelligence
Classifier: Programming Language :: C++
Classifier: Programming Language :: Python :: 3
Classifier: Programming Language :: Python :: 3.9
Classifier: Programming Language :: Python :: 3.10
Classifier: Programming Language :: Python :: 3.11
Classifier: Programming Language :: Python :: 3.12
Classifier: Programming Language :: Python :: 3 :: Only
Classifier: Programming Language :: Python :: Implementation :: CPython
Classifier: Operating System :: POSIX
Classifier: Operating System :: Unix
Classifier: Operating System :: MacOS
Requires-Python: >=3.9
License-File: LICENSE
Requires-Dist: shapely>=2.0.0
Requires-Dist: torch<2.8.0,>=2.7.0
Provides-Extra: test
Requires-Dist: pytest>=8.0.0; extra == "test"
Requires-Dist: numpy<2.0.0,>=1.4.0; extra == "test"
Dynamic: license-file
